sphinx_foundation_theme/.__init__.py.swp
sphinx_foundation_theme/__init__.py
sphinx_foundation_theme/foundation/layout.html
sphinx_foundation_theme/foundation/localtoc.html
sphinx_foundation_theme/foundation/theme.conf
sphinx_foundation_theme/foundation/topbar.html
sphinx_foundation_theme/foundation/static/foundation-sphinx.css_t
sphinx_foundation_theme/foundation/static/foundation-sites/default.min.css
sphinx_foundation_theme/foundation/static/foundation-sites/foundation.min.js
sphinx_foundation_theme/foundation/static/what-input/what-input.min.js
sphinx-foundation-theme-0.6.0.dist-info/WHEEL
sphinx-foundation-theme-0.6.0.dist-info/METADATA
sphinx-foundation-theme-0.6.0.dist-info/RECORD
