Metadata-Version: 1.2
Name: sphinx-foundation-theme
Version: 0.6.0
Summary: A Sphinx HTML theme that uses Zurb foundation-sites.
Home-page: https://thewtex.github.io/sphinx-foundation-theme/
License: UNKNOWN
Author: Matt McCormick
Author-email: matt.mccormick@kitware.com
Classifier: Development Status :: 4 - Beta
Classifier: Environment :: Web Environment
Classifier: Intended Audience :: Developers
Classifier: License :: OSI Approved :: MIT License
Classifier: Operating System :: OS Independent
Classifier: Topic :: Documentation :: Sphinx
Classifier: Topic :: Internet
Classifier: Topic :: Software Development :: Documentation
Requires-Dist: sphinx
